.bumpversion.cfg
.cookiecutterrc
.coveragerc
.editorconfig
.gitignore
.pre-commit-config.yaml
.readthedocs.yml
AUTHORS.rst
CHANGELOG.rst
CONTRIBUTING.rst
LICENSE
MANIFEST.in
README.rst
pyproject.toml
pytest.ini
setup.py
tox.ini
.github/workflows/github-actions.yml
ci/bootstrap.py
ci/requirements.txt
ci/templates/.github/workflows/github-actions.yml
docs/authors.rst
docs/changelog.rst
docs/conf.py
docs/contributing.rst
docs/index.rst
docs/installation.rst
docs/readme.rst
docs/requirements.txt
docs/spelling_wordlist.txt
docs/usage.rst
docs/reference/index.rst
docs/reference/signalfd.rst
src/signalfd/__init__.py
src/signalfd/_signalfd_build.py
src/signalfd.egg-info/PKG-INFO
src/signalfd.egg-info/SOURCES.txt
src/signalfd.egg-info/dependency_links.txt
src/signalfd.egg-info/not-zip-safe
src/signalfd.egg-info/requires.txt
src/signalfd.egg-info/top_level.txt
tests/test_signalfd.py
tests/test_sigprocmask.py